actransit/__init__.py
actransit/actransit.py
actransit/exceptions.py
python_actransit-0.1.6.dist-info/LICENSE
python_actransit-0.1.6.dist-info/METADATA
python_actransit-0.1.6.dist-info/WHEEL
python_actransit-0.1.6.dist-info/top_level.txt
python_actransit-0.1.6.dist-info/RECORD
